db_reconnect/__init__.py
db_reconnect/core.py
db_reconnect/decorators.py
db_reconnect/middleware.py
bear_django_db_reconnect-0.1.0.dist-info/METADATA
bear_django_db_reconnect-0.1.0.dist-info/WHEEL
bear_django_db_reconnect-0.1.0.dist-info/top_level.txt
bear_django_db_reconnect-0.1.0.dist-info/RECORD
