Metadata-Version: 2.4
Name: bear-django-db-reconnect
Version: 0.1.0
Summary: A Django middleware and decorator to automatically handle database connection losses.
Author-email: Bohdan Riabunets <bearablyk@gmail.com>
License-Expression: MIT
Project-URL: Homepage, https://github.com/bearablyk/django-db-reconnect
Project-URL: Issues, https://github.com/bearablyk/django-db-reconnect/issues
Classifier: Programming Language :: Python :: 3
Classifier: Operating System :: OS Independent
Classifier: Framework :: Django
Classifier: Framework :: Django :: 3.2
Classifier: Framework :: Django :: 4.0
Classifier: Framework :: Django :: 4.2
Requires-Python: >=3.8
Requires-Dist: Django>=3.2
